voxelfuse_primitives/__init__.py
voxelfuse_primitives/linkage.py
voxelfuse_primitives/solid.py
voxelfuse_primitives-1.0.3.dist-info/LICENSE.md
voxelfuse_primitives-1.0.3.dist-info/METADATA
voxelfuse_primitives-1.0.3.dist-info/WHEEL
voxelfuse_primitives-1.0.3.dist-info/top_level.txt
voxelfuse_primitives-1.0.3.dist-info/RECORD
