Metadata-Version: 2.1
Name: voxelfuse-primitives
Version: 1.0.3
Summary: Classes for generating primitives using the VoxelFuse library
Home-page: https://github.com/cdbrauer/VoxelFuse-Primitives
Author: Cole Brauer
License: UNKNOWN
Platform: UNKNOWN
Classifier: Programming Language :: Python :: 3
Classifier: License :: OSI Approved :: GNU General Public License v3 (GPLv3)
Classifier: Operating System :: OS Independent
Requires-Dist: voxelfuse (>=1.1.1)
Requires-Dist: numpy
Requires-Dist: pyqt5
Requires-Dist: numba
